{
  "name": "business",
  "base": "PersistedModel",
  "strict": false,
  "idInjection": false,
  "options": {
    "validateUpsert": true
  },
  "properties": {
    "id": {
      "type": "string",
      "id": true
    },
    "isActive": {
      "type": "boolean"
    },
    "company": {
      "type": "string"
    },
    "email": {
      "type": "string"
    },
    "address": {
      "type": "string"
    },
    "latitude": {
      "type": "number"
    },
    "longitude": {
      "type": "number"
    }
  },
  "validations": [],
  "relations": {},
  "acls": [],
  "methods": []
}
